juce_rsa.cp38-win_amd64.pyd
juce_rsa-0.1.dist-info/LICENSE
juce_rsa-0.1.dist-info/METADATA
juce_rsa-0.1.dist-info/WHEEL
juce_rsa-0.1.dist-info/top_level.txt
juce_rsa-0.1.dist-info/RECORD
