Metadata-Version: 2.1
Name: juce-rsa
Version: 0.1
Summary: Python bindings for juce::RSAKey
Home-page: https://github.com/sevangelatos/juce_rsa
Author: sevangelatos
Author-email: sevangelatos_at_@gmail.com
License: UNKNOWN
Platform: UNKNOWN
Classifier: Development Status :: 4 - Beta
Classifier: Intended Audience :: Developers
Classifier: Environment :: Win32 (MS Windows)
Classifier: Environment :: MacOS X
Classifier: Operating System :: POSIX :: Linux
Classifier: Operating System :: Microsoft :: Windows
Classifier: Operating System :: MacOS :: MacOS X
Classifier: License :: OSI Approved :: MIT License
Classifier: Programming Language :: C++
Classifier: Programming Language :: Python :: 3 :: Only
Classifier: Topic :: Security :: Cryptography
Classifier: Topic :: Security
Classifier: Topic :: Utilities
Requires-Python: >=3.6
